akeyless_grpc/__init__.py
akeyless_grpc/models/__init__.py
akeyless_grpc/models/access_or_group_permission_assignment_pb2.py
akeyless_grpc/models/access_or_group_permission_assignment_pb2_grpc.py
akeyless_grpc/models/attribute_type_and_value_pb2.py
akeyless_grpc/models/attribute_type_and_value_pb2_grpc.py
akeyless_grpc/models/auth_output_pb2.py
akeyless_grpc/models/auth_output_pb2_grpc.py
akeyless_grpc/models/auth_pb2.py
akeyless_grpc/models/auth_pb2_grpc.py
akeyless_grpc/models/bastion_list_entry_pb2.py
akeyless_grpc/models/bastion_list_entry_pb2_grpc.py
akeyless_grpc/models/bastions_list_pb2.py
akeyless_grpc/models/bastions_list_pb2_grpc.py
akeyless_grpc/models/certificate_chain_info_pb2.py
akeyless_grpc/models/certificate_chain_info_pb2_grpc.py
akeyless_grpc/models/certificate_expiration_event_pb2.py
akeyless_grpc/models/certificate_expiration_event_pb2_grpc.py
akeyless_grpc/models/certificate_info_pb2.py
akeyless_grpc/models/certificate_info_pb2_grpc.py
akeyless_grpc/models/certificate_issue_info_pb2.py
akeyless_grpc/models/certificate_issue_info_pb2_grpc.py
akeyless_grpc/models/certificate_template_info_pb2.py
akeyless_grpc/models/certificate_template_info_pb2_grpc.py
akeyless_grpc/models/certificate_version_info_pb2.py
akeyless_grpc/models/certificate_version_info_pb2_grpc.py
akeyless_grpc/models/classic_key_details_info_pb2.py
akeyless_grpc/models/classic_key_details_info_pb2_grpc.py
akeyless_grpc/models/classic_key_status_info_pb2.py
akeyless_grpc/models/classic_key_status_info_pb2_grpc.py
akeyless_grpc/models/classic_key_target_info_pb2.py
akeyless_grpc/models/classic_key_target_info_pb2_grpc.py
akeyless_grpc/models/create_secret_output_pb2.py
akeyless_grpc/models/create_secret_output_pb2_grpc.py
akeyless_grpc/models/create_secret_pb2.py
akeyless_grpc/models/create_secret_pb2_grpc.py
akeyless_grpc/models/delete_item_output_pb2.py
akeyless_grpc/models/delete_item_output_pb2_grpc.py
akeyless_grpc/models/delete_item_pb2.py
akeyless_grpc-0.0.1.dist-info/METADATA
akeyless_grpc-0.0.1.dist-info/WHEEL
akeyless_grpc-0.0.1.dist-info/top_level.txt
akeyless_grpc-0.0.1.dist-info/RECORD
